{
    "metadata":{
        "type":"Object",
        "version":4.4,
        "sourceFile":"tym_stage2.blend",
        "generator":"io_three"
    },
    "object":{
        "type":"Scene",
        "matrix":[1,0,0,0,0,1,0,0,0,0,1,0,0,0,0,1],
        "uuid":"055E6FB9-4706-46AE-BB89-3743314F88AE",
        "children":[{
            "name":"Plane",
            "uuid":"2CA5908F-832C-458E-9641-511BA77E9800",
            "matrix":[-1,0,0,0,0,0,1,0,0,1,0,0,0,0,0,1],
            "visible":true,
            "type":"Mesh",
            "castShadow":false,
            "receiveShadow":false,
            "geometry":"EFD0D5B4-DBDB-4057-8EA1-2708AF7DCF3F"
        }]
    },
    "geometries":[{
        "type":"BufferGeometry",
        "name":"Plane.011Geometry",
        "data":{
            "index":{
                "array":[0,1,2,3,4,5,2,5,0,3,6,7,8,9,6,10,11,12,0,13,1,3,7,4,2,3,5,3,8,6,8,14,9,10,15,11],
                "type":"Uint16Array",
                "itemSize":1
            },
            "attributes":{
                "position":{
                    "array":[-1,2,0,1,-2,0,1,2,0,1,13.3516,0,-1,15.3547,0,-1,13.3516,0,10.1697,15.3547,0,1,15.3547,0,10.1697,13.3516,0,12.2582,15.3547,0,10.1697,13.3516,0,12.2582,-1.86733,0,12.2582,13.3516,0,-1,-2,0,12.2582,13.3516,0,10.1697,-1.86733,0],
                    "type":"Float32Array",
                    "itemSize":3
                },
                "normal":{
                    "array":[0,-0,1,0,-0,1,0,-0,1,-0,-0,1,-0,-0,1,-0,-0,1,-0,0,1,-0,0,1,-0,0,1,-0,0,1,0,-0,1,0,-0,1,0,-0,1,0,-0,1,-0,-0,1,0,-0,1],
                    "type":"Float32Array",
                    "itemSize":3
                }
            }
        },
        "uuid":"EFD0D5B4-DBDB-4057-8EA1-2708AF7DCF3F"
    }],
    "textures":[],
    "animations":[{
        "name":"default",
        "tracks":[],
        "fps":24
    }],
    "images":[],
    "materials":[]
}